[{
    "date": "2025-06-08",
    "time": "17:00",
    "event": "Robin Maxime, Abbaye de Tournus",
    "source": "concert",
    "group": "Saone et Loire"
  },
{
    "date": "2025-06-08",
    "time": "10:00",
    "event": "Festi Palestine, Morlay",
    "source": "concert",
    "group": "Saone et Loire"
  },
{
    "date": "2025-05-30",
    "time": "18:30",
    "event": "Festival Grange ta cour",
    "source": "concert",
    "group": "Saone et Loire"
  },
    {
    "date": "2025-05-31",
    "time": "21:00",
    "event": "UEFA Final Champions League",
    "source": "sport",
    "group": "Paris"
  }
]
